LICENSE
pyproject.toml
setup.py
sri/__init__.py
sri/bootstrap.py
sri/utils.py
sriracha/__init__.py
sriracha/application.py
sriracha/controller.py
sriracha/request.py
sriracha/utils.py
sriracha/view.py
sriracha.egg-info/PKG-INFO
sriracha.egg-info/SOURCES.txt
sriracha.egg-info/dependency_links.txt
sriracha.egg-info/entry_points.txt
sriracha.egg-info/requires.txt
sriracha.egg-info/top_level.txt