Metadata-Version: 2.1
Name: sriracha
Version: 0.1.1
Summary: MVC Web Framework
Home-page: UNKNOWN
Author: pcranaway
Author-email: pcranaway@tuta.io
License: GPL
Platform: UNKNOWN
License-File: LICENSE
